edfh_data/__init__.py
edfh_data/exceptions.py
edfh_data/models.py
edfh_data/db/__init__.py
edfh_data/db/crud.py
edfh_data/db/models.py
edfh_data/db/utils.py
edfh_data/eddn/__init__.py
edfh_data/eddn/handlers.py
edfh_data/eddn/listener.py
edfh_data-0.12.0.dist-info/licenses/LICENSE
edfh_data-0.12.0.dist-info/METADATA
edfh_data-0.12.0.dist-info/WHEEL
edfh_data-0.12.0.dist-info/entry_points.txt
edfh_data-0.12.0.dist-info/top_level.txt
edfh_data-0.12.0.dist-info/RECORD
