Metadata-Version: 2.4
Name: edfh-data
Version: 0.12.0
Summary: Python library for the E:D Faction Hub application backend data services
License-Expression: MIT
Project-URL: Homepage, https://codeberg.org/jdlbt/edfh-data
Project-URL: Issue tracker, https://codeberg.org/jdlbt/edfh-data/issues
Project-URL: Source, https://codeberg.org/jdlbt/edfh-data
Classifier: Development Status :: 2 - Pre-Alpha
Classifier: Intended Audience :: Developers
Classifier: Programming Language :: Python
Classifier: Programming Language :: Python :: 3 :: Only
Classifier: Programming Language :: Python :: 3.13
Classifier: Programming Language :: Python :: 3.14
Requires-Python: >=3.13
License-File: LICENSE
Requires-Dist: fdev-ids
Requires-Dist: pydantic
Provides-Extra: db
Requires-Dist: PyMySQL; extra == "db"
Requires-Dist: sqlmodel; extra == "db"
Provides-Extra: eddn
Requires-Dist: edfh-data[db]; extra == "eddn"
Requires-Dist: orjson; extra == "eddn"
Requires-Dist: pika; extra == "eddn"
Requires-Dist: structlog; extra == "eddn"
Requires-Dist: zmq; extra == "eddn"
Provides-Extra: dev
Requires-Dist: edfh-data[db,eddn]; extra == "dev"
Requires-Dist: alembic; extra == "dev"
Requires-Dist: black==25.9.0; extra == "dev"
Requires-Dist: build; extra == "dev"
Requires-Dist: flake8==7.3.0; extra == "dev"
Requires-Dist: isort==6.1.0; extra == "dev"
Requires-Dist: pre-commit; extra == "dev"
Requires-Dist: python-dotenv; extra == "dev"
Requires-Dist: twine; extra == "dev"
Dynamic: license-file
